mm_balance/__init__.py
mm_balance/balance_fetcher.py
mm_balance/cli.py
mm_balance/command_runner.py
mm_balance/config.py
mm_balance/constants.py
mm_balance/diff.py
mm_balance/price.py
mm_balance/result.py
mm_balance/rpc.py
mm_balance/token_decimals.py
mm_balance/utils.py
mm_balance/config/example.toml
mm_balance/output/__init__.py
mm_balance/output/utils.py
mm_balance/output/formats/__init__.py
mm_balance/output/formats/json_format.py
mm_balance/output/formats/table_format.py
mm_balance-0.6.1.dist-info/METADATA
mm_balance-0.6.1.dist-info/WHEEL
mm_balance-0.6.1.dist-info/entry_points.txt
mm_balance-0.6.1.dist-info/RECORD
