Metadata-Version: 2.4
Name: mm-balance
Version: 0.6.1
Requires-Python: >=3.14
Requires-Dist: deepdiff==8.6.1
Requires-Dist: mm-apt==0.5.1
Requires-Dist: mm-btc==0.5.6
Requires-Dist: mm-concurrency~=0.1.0
Requires-Dist: mm-eth==0.7.4
Requires-Dist: mm-sol==0.7.4
